greenremover/__init__py
greenremover/cli.py
greenremover/core.py
greenremover-0.1.0.dist-info/METADATA
greenremover-0.1.0.dist-info/WHEEL
greenremover-0.1.0.dist-info/entry_points.txt
greenremover-0.1.0.dist-info/licenses/LICENSE
greenremover-0.1.0.dist-info/RECORD
