Metadata-Version: 2.4
Name: greenremover
Version: 0.1.0
Summary: A lightweight Python tool for removing green screen backgrounds from images, converting them into transparent PNGs for easy compositing and editing.
Project-URL: Homepage, https://github.com/avatarreal/greenremover
Project-URL: Bug Tracker, https://github.com/avatarreal/greenremover/issues
Author-email: avatarreal <avatarreal@users.noreply.github.com>
License: MIT
License-File: LICENSE
Keywords: background removal,chroma key,green screen,image processing
Requires-Python: >=3.10
Requires-Dist: numpy<2.0.0
Requires-Dist: pillow<11.0.0,>=10.0.0
